bicycle_bell_seds/__init__.py
bicycle_bell_seds/callbacks.py
bicycle_bell_seds/jn_seds_cli.py
seds_cli/__init__.py
seds_cli/seds_cli.py
seds_cli/seds_constants.py
seds_cli/res/logs/.gitkeep
seds_cli/res/models/.gitkeep
seds_cli/res/models/crnn-history.json
seds_cli/res/models/yamnet_extended-history.json
seds_cli/res/models/crnn/keras_metadata.pb
seds_cli/res/models/crnn/saved_model.pb
seds_cli/res/models/crnn/variables/variables.data-00000-of-00001
seds_cli/res/models/crnn/variables/variables.index
seds_cli/res/models/yamnet_base/keras_metadata.pb
seds_cli/res/models/yamnet_base/saved_model.pb
seds_cli/res/models/yamnet_base/assets/yamnet_class_map.csv
seds_cli/res/models/yamnet_base/variables/variables.data-00000-of-00001
seds_cli/res/models/yamnet_base/variables/variables.index
seds_cli/res/models/yamnet_extended/keras_metadata.pb
seds_cli/res/models/yamnet_extended/saved_model.pb
seds_cli/res/models/yamnet_extended/assets/yamnet_class_map.csv
seds_cli/res/models/yamnet_extended/variables/variables.data-00000-of-00001
seds_cli/res/models/yamnet_extended/variables/variables.index
seds_cli/res/records/.gitkeep
seds_cli/res/test-files/.gitkeep
seds_cli/res/test-files/mini-test.csv
seds_cli/res/test-files/mini-test.wav
seds_cli/seds_lib/__init__.py
seds_cli/seds_lib/software.py
seds_cli/seds_lib/systems.py
seds_cli/seds_lib/data/__init__.py
seds_cli/seds_lib/data/audio/__init__.py
seds_cli/seds_lib/data/audio/chunks.py
seds_cli/seds_lib/data/audio/elements.py
seds_cli/seds_lib/data/configs/__init__.py
seds_cli/seds_lib/data/configs/configs.py
seds_cli/seds_lib/data/predictions/__init__.py
seds_cli/seds_lib/data/predictions/results.py
seds_cli/seds_lib/data/time/__init__.py
seds_cli/seds_lib/data/time/delay.py
seds_cli/seds_lib/models/__init__.py
seds_cli/seds_lib/models/inference_models.py
seds_cli/seds_lib/models/saved_models.py
seds_cli/seds_lib/selectors/__init__.py
seds_cli/seds_lib/selectors/selectors.py
seds_cli/seds_lib/storage/__init__.py
bicycle_bell_seds_cli-0.0.3.dist-info/LICENSE
bicycle_bell_seds_cli-0.0.3.dist-info/METADATA
bicycle_bell_seds_cli-0.0.3.dist-info/WHEEL
bicycle_bell_seds_cli-0.0.3.dist-info/entry_points.txt
bicycle_bell_seds_cli-0.0.3.dist-info/top_level.txt
bicycle_bell_seds_cli-0.0.3.dist-info/RECORD
