Metadata-Version: 2.1
Name: bicycle-bell-seds-cli
Version: 0.0.3
Summary: CLI software for the detection of the single target sound event of bicycle bell signals.
Home-page: https://github.com/ClemensKubach/bicycle-bell-sed-software
Author: Clemens Kubach
Author-email: clemens.kubach@gmail.com
License: MIT License
Project-URL: Bug Tracker, https://github.com/ClemensKubach/bicycle-bell-sed-software/issues
Platform: UNKNOWN
License-File: LICENSE
Requires-Dist: tensorflow (<=2.8.0,>=2.6.2)
Requires-Dist: pyaudio (>=0.2.11)
Requires-Dist: fire (>=0.4.0)
Requires-Dist: numpy (>=1.19.0)
Requires-Dist: tensorflow-io (>=0.21.0)
Requires-Dist: dataclasses (>=0.8) ; python_version < "3.7"
